huntflow_base_metrics-0.2.1.dist-info/METADATA
huntflow_base_metrics-0.2.1.dist-info/WHEEL
huntflow_base_metrics-0.2.1.dist-info/entry_points.txt
huntflow_base_metrics-0.2.1.dist-info/licenses/LICENSE
huntflow_base_metrics/__init__.py
huntflow_base_metrics/_context.py
huntflow_base_metrics/base.py
huntflow_base_metrics/export.py
huntflow_base_metrics/web_frameworks/__init__.py
huntflow_base_metrics/web_frameworks/_middleware.py
huntflow_base_metrics/web_frameworks/_request_metrics.py
huntflow_base_metrics/web_frameworks/aiohttp.py
huntflow_base_metrics/web_frameworks/fastapi.py
huntflow_base_metrics/web_frameworks/litestar.py
huntflow_base_metrics-0.2.1.dist-info/RECORD
