Metadata-Version: 2.1
Name: huntflow-base-metrics
Version: 0.2.1
Summary: Prometheus metrics for Huntflow services
Author-Email: Developers huntflow <developer@huntflow.ru>
License: MIT
Classifier: Programming Language :: Python :: 3
Classifier: Programming Language :: Python :: 3.8
Classifier: Programming Language :: Python :: 3.9
Classifier: Programming Language :: Python :: 3.10
Classifier: Programming Language :: Python :: 3.11
Classifier: Programming Language :: Python :: 3.12
Classifier: Programming Language :: Python :: 3.13
Requires-Python: >=3.8
Requires-Dist: prometheus-client>=0.21.0
Requires-Dist: aiofiles>=24.1.0
Requires-Dist: types-aiofiles>=24.1.0.20240626
